{
    "keep": {
        "days": true,
        "amount": 14
    },
    "auditLog": "Public\\logs\\.9316c7e79eca7e8741f47ad7ad1386ed3caf48e7-audit.json",
    "files": [
        {
            "date": 1759506396988,
            "name": "Public\\logs\\application-2025-10-03.log",
            "hash": "407033a5e391265cc36ec4883253a19c658a7f3a7198b072a5a1d49bfe1a2ba7"
        },
        {
            "date": 1759594432938,
            "name": "Public\\logs\\application-2025-10-04.log",
            "hash": "cff9a4d06bb712ecbf4a2c965216a7707efc9f00af5e7283edc78f30296f8f6a"
        }
    ],
    "hashType": "sha256"
}